monstr/__about__.py
monstr/__init__.py
monstr/encrypt.py
monstr/entities.py
monstr/exception.py
monstr/giftwrap.py
monstr/inbox.py
monstr/util.py
monstr/channels/__init__.py
monstr/channels/channel.py
monstr/channels/event_handlers.py
monstr/channels/persist.py
monstr/client/__init__.py
monstr/client/client.py
monstr/client/event_handlers.py
monstr/client/messaging.py
monstr/data/__init__.py
monstr/data/data.py
monstr/db/__init__.py
monstr/db/db.py
monstr/event/__init__.py
monstr/event/event.py
monstr/event/event_handlers.py
monstr/event/expire.py
monstr/event/persist.py
monstr/event/persist_memory.py
monstr/event/persist_postgres.py
monstr/event/persist_sqlite.py
monstr/event/persist_test.py
monstr/ident/__init__.py
monstr/ident/alias.py
monstr/ident/event_handlers.py
monstr/ident/keystore.py
monstr/ident/persist.py
monstr/ident/persist_test.py
monstr/ident/profile.py
monstr/relay/__init__.py
monstr/relay/accept_handlers.py
monstr/relay/exceptions.py
monstr/relay/relay.py
monstr/relay/tor.py
monstr/settings/__init__.py
monstr/settings/handler.py
monstr/settings/persist.py
monstr/signing/__init__.py
monstr/signing/nip46.py
monstr/signing/signing.py
monstr/spam_handlers/__init__.py
monstr/spam_handlers/spam_handlers.py
monstr-0.1.9.dist-info/METADATA
monstr-0.1.9.dist-info/WHEEL
monstr-0.1.9.dist-info/licenses/LICENSE
monstr-0.1.9.dist-info/RECORD
