Metadata-Version: 2.3
Name: monstr
Version: 0.1.9
Summary: Monstr: Python Nostr module. Python code for working with nostr.
Project-URL: Documentation, https://github.com/monty888/monstr/blob/master/README.md
Project-URL: Issues, https://github.com/monty888/monstr/issues
Project-URL: Source, https://github.com/monty888/monstr
Author-email: Monty888 <Monty888@protonmail.com>
License-Expression: MIT
License-File: LICENSE
Requires-Dist: aioconsole>=0.6.0
Requires-Dist: aiohttp>=3.8.4
Requires-Dist: aiosqlite>=0.18.0
Requires-Dist: bech32>=1.2.0
Requires-Dist: cachetools>=5.3.0
Requires-Dist: cryptography>=39.0.1
Requires-Dist: pycryptodome>=3.20.0
Requires-Dist: secp256k1>=0.14.0
